sm_icon_extractor/__init__.py
sm_icon_extractor/__main__.py
sm_icon_extractor-1.0.2.dist-info/LICENSE
sm_icon_extractor-1.0.2.dist-info/METADATA
sm_icon_extractor-1.0.2.dist-info/WHEEL
sm_icon_extractor-1.0.2.dist-info/entry_points.txt
sm_icon_extractor-1.0.2.dist-info/top_level.txt
sm_icon_extractor-1.0.2.dist-info/RECORD
