Metadata-Version: 2.1
Name: sm-icon-extractor
Version: 1.0.2
Summary: Extracts icons from Scrap Mechanic.
Home-page: https://git.brokenmouse.studio/ever/sm-icon-extractor
Author: EV3R4
Author-email: ever@brokenmouse.studio
Classifier: License :: OSI Approved :: BSD License
Classifier: Programming Language :: Python :: 3
Classifier: Operating System :: OS Independent
Requires-Python: >=3.9
License-File: LICENSE
Requires-Dist: Pillow
Requires-Dist: pyjson5
